apngasm_python/_apngasm_python.pypy310-pp73-darwin.so
apngasm_python/__init__.py
apngasm_python/_apngasm_python.pyi
apngasm_python/py.typed
apngasm_python/apngasm.py
apngasm_python-1.3.2.dist-info/RECORD
apngasm_python-1.3.2.dist-info/LICENSE
apngasm_python-1.3.2.dist-info/WHEEL
apngasm_python-1.3.2.dist-info/entry_points.txt
apngasm_python-1.3.2.dist-info/METADATA
