Metadata-Version: 2.1
Name: apngasm-python
Version: 1.3.2
Summary: A nanobind python API for apngasm, a tool/library for APNG assembly & disassembly with compression support.
Keywords: apng png nanobind pybind11
Author-Email: chaudominic <chaudominic2@gmail.com>
License:                   GNU LESSER GENERAL PUBLIC LICENSE
Classifier: Topic :: Multimedia :: Graphics
Project-URL: Repository, https://github.com/laggykiller/apngasm-python
Project-URL: Documentation, https://apngasm-python.readthedocs.io/en/latest/
Project-URL: Tracker, https://github.com/laggykiller/apngasm-python/issues
Requires-Python: >=3.8
Provides-Extra: full
Provides-Extra: test
Provides-Extra: lint
Requires-Dist: Pillow; extra == "full"
Requires-Dist: numpy; extra == "full"
Requires-Dist: pytest; extra == "test"
Requires-Dist: ruff; extra == "lint"
Requires-Dist: mypy; extra == "lint"
Requires-Dist: isort; extra == "lint"
Requires-Dist: types-Pillow; extra == "lint"
